Humanitec/Humanitec.py
Humanitec/__init__.py
robotframework_humanitec-0.1.1.dist-info/LICENSE.txt
robotframework_humanitec-0.1.1.dist-info/METADATA
robotframework_humanitec-0.1.1.dist-info/WHEEL
robotframework_humanitec-0.1.1.dist-info/top_level.txt
robotframework_humanitec-0.1.1.dist-info/RECORD
