Metadata-Version: 2.1
Name: robotframework-humanitec
Version: 0.1.1
Summary: Keywords for Humanitec REST api
Home-page: https://gitlab.com/noordsestern/robotframework-humanitec
Author: Markus Stahl
Author-email: markus.i.sverige@googlemail.com
License: EUPL 1.2
Classifier: Intended Audience :: Developers
Classifier: Natural Language :: English
Classifier: Programming Language :: Python :: 3
Classifier: Topic :: Software Development
Classifier: License :: OSI Approved :: European Union Public Licence 1.2 (EUPL 1.2)
Classifier: Operating System :: OS Independent
Classifier: Development Status :: 3 - Alpha
Classifier: Framework :: Robot Framework :: Library
Classifier: Typing :: Typed
License-File: LICENSE.txt
Requires-Dist: robotframework
Requires-Dist: requests
Requires-Dist: unofficial-humanitec-client
